{
    "startdate": "20220923",
    "fullstartdate": "202209231600",
    "enddate": "20220924",
    "url": "https://www.bing.com/th?id=OHR.DarkSkyAcadia_ZH-CN1827511700_1920x1080.jpg&rf=LaDigue_1920x1080.jpg&pid=hp",
    "urlbase": "/th?id=OHR.DarkSkyAcadia_ZH-CN1827511700",
    "copyright": "阿卡迪亚国家公园上空的银河系，美国缅因州 (© Harry Collins/Getty Images)",
    "copyrightlink": "https://www.bing.com/search?q=%E9%98%BF%E5%8D%A1%E8%BF%AA%E4%BA%9A%E5%9B%BD%E5%AE%B6%E5%85%AC%E5%9B%AD&form=hpcapt&mkt=zh-cn",
    "title": "繁星闪烁的夜晚",
    "quiz": "/search?q=Bing+homepage+quiz&filters=WQOskey:%22HPQuiz_20220923_DarkSkyAcadia%22&FORM=HPQUIZ",
    "wp": true,
    "hsh": "5b0fbd67bc112bea79a999049f19afe8",
    "drk": 1,
    "top": 1,
    "bot": 1,
    "hs": []
}