{
    "startdate": "20240414",
    "fullstartdate": "202404141600",
    "enddate": "20240415",
    "url": "https://www.bing.com/th?id=OHR.ChambordCastle_ZH-CN0930093515_1920x1080.jpg&rf=LaDigue_1920x1080.jpg&pid=hp",
    "urlbase": "/th?id=OHR.ChambordCastle_ZH-CN0930093515",
    "copyright": "香波城堡，中央-卢瓦尔河谷大区，法国 (© Susanne Kremer/eStock Photo)",
    "copyrightlink": "https://www.bing.com/search?q=%E9%A6%99%E6%B3%A2%E5%9F%8E%E5%A0%A1&form=hpcapt&mkt=zh-cn",
    "title": "介于文艺复兴与独创性之间",
    "quiz": "/search?q=Bing+homepage+quiz&filters=WQOskey:%22HPQuiz_20240414_ChambordCastle%22&FORM=HPQUIZ",
    "wp": true,
    "hsh": "d8fb1b1a61d29d118a23aa8a6c5e543e",
    "drk": 1,
    "top": 1,
    "bot": 1,
    "hs": []
}