{
    "startdate": "20230730",
    "fullstartdate": "202307301600",
    "enddate": "20230731",
    "url": "https://www.bing.com/th?id=OHR.RockHouse_ZH-CN7318310409_1920x1080.jpg&rf=LaDigue_1920x1080.jpg&pid=hp",
    "urlbase": "/th?id=OHR.RockHouse_ZH-CN7318310409",
    "copyright": "霍金山州立公园的岩石屋，俄亥俄州，美国 (© Kenneth Keifer/Getty Images)",
    "copyrightlink": "https://www.bing.com/search?q=%E4%BF%84%E4%BA%A5%E4%BF%84%E5%B7%9E&form=hpcapt&mkt=zh-cn",
    "title": "有人在家吗?",
    "quiz": "/search?q=Bing+homepage+quiz&filters=WQOskey:%22HPQuiz_20230730_RockHouse%22&FORM=HPQUIZ",
    "wp": true,
    "hsh": "45253626f6bcb2e769723f0a68450a76",
    "drk": 1,
    "top": 1,
    "bot": 1,
    "hs": []
}