{
    "startdate": "20230505",
    "fullstartdate": "202305051600",
    "enddate": "20230506",
    "url": "https://www.bing.com/th?id=OHR.Kornblume_ZH-CN0344238832_1920x1080.jpg&rf=LaDigue_1920x1080.jpg&pid=hp",
    "urlbase": "/th?id=OHR.Kornblume_ZH-CN0344238832",
    "copyright": "大麦和矢车菊, 诺德豪森, 德国 (© Mandy Tabatt/Getty Images)",
    "copyrightlink": "https://www.bing.com/search?q=%E7%9F%A2%E8%BD%A6%E8%8F%8A&form=hpcapt&mkt=zh-cn",
    "title": "一片花田",
    "quiz": "/search?q=Bing+homepage+quiz&filters=WQOskey:%22HPQuiz_20230505_Kornblume%22&FORM=HPQUIZ",
    "wp": true,
    "hsh": "3316993bc80998a54b6d9c802ae9b821",
    "drk": 1,
    "top": 1,
    "bot": 1,
    "hs": []
}