{
    "startdate": "20240220",
    "fullstartdate": "202402201600",
    "enddate": "20240221",
    "url": "https://www.bing.com/th?id=OHR.YosemiteFirefall_ZH-CN2236242565_1920x1080.jpg&rf=LaDigue_1920x1080.jpg&pid=hp",
    "urlbase": "/th?id=OHR.YosemiteFirefall_ZH-CN2236242565",
    "copyright": "火瀑布，优胜美地国家公园，加利福尼亚州，美国 (© Gregory B Cuvelier/Shutterstock)",
    "copyrightlink": "https://www.bing.com/search?q=%E7%81%AB%E7%80%91%E5%B8%83&form=hpcapt&mkt=zh-cn",
    "title": "一个天然的矛盾体",
    "quiz": "/search?q=Bing+homepage+quiz&filters=WQOskey:%22HPQuiz_20240220_YosemiteFirefall%22&FORM=HPQUIZ",
    "wp": true,
    "hsh": "c26e8ad0f327e2c8132fc300652fdf01",
    "drk": 1,
    "top": 1,
    "bot": 1,
    "hs": []
}